victoria_rebuilder/__init__.py
victoria_rebuilder/cli.py
victoria_rebuilder/client.py
victoria_rebuilder/config.py
victoria_rebuilder/rebuild.py
victoria_rebuilder-0.2.2.dist-info/LICENSE
victoria_rebuilder-0.2.2.dist-info/METADATA
victoria_rebuilder-0.2.2.dist-info/WHEEL
victoria_rebuilder-0.2.2.dist-info/top_level.txt
victoria_rebuilder-0.2.2.dist-info/RECORD
