Metadata-Version: 2.1
Name: victoria-rebuilder
Version: 0.2.2
Summary: Victoria Plugin that allows the creation and DESTRUCTION of SAAS on the cloud.
Home-page: UNKNOWN
Author: Alex Potter-Dixon
License: UNKNOWN
Platform: UNKNOWN
Requires-Dist: click
Requires-Dist: marshmallow
Requires-Dist: pyyaml
Requires-Dist: requests
Requires-Dist: azure-devops
Requires-Dist: victoria
